Metadata-Version: 1.0
Name: PoL-gauss-bino-distribution
Version: 0.2
Summary: Gaussian & Binomial distributions
Home-page: UNKNOWN
Author: UNKNOWN
Author-email: saxenak02@gmail.com
License: UNKNOWN
Platform: UNKNOWN
